django_orm_sugar.py
django_orm_sugar-0.3.2.dist-info/DESCRIPTION.rst
django_orm_sugar-0.3.2.dist-info/METADATA
django_orm_sugar-0.3.2.dist-info/RECORD
django_orm_sugar-0.3.2.dist-info/WHEEL
django_orm_sugar-0.3.2.dist-info/metadata.json
django_orm_sugar-0.3.2.dist-info/top_level.txt
