Metadata-Version: 2.0
Name: django-orm-sugar
Version: 0.3.2
Summary: Django ORM sugar library to simplify querying
Home-page: https://github.com/Nepherhotep/django-orm-sugar
Author: Alexey Zankevich
Author-email: alex.zankevich@gmail.com
License: MIT
Keywords: Django,ORM,util,sugar
Platform: Platform Independent
Classifier: Framework :: Django :: 1.8
Classifier: Development Status :: 5 - Production/Stable
Classifier: Programming Language :: Python :: 2.7
Classifier: Programming Language :: Python :: 3.0
Classifier: Programming Language :: Python :: 3.1
Classifier: Programming Language :: Python :: 3.2
Classifier: Programming Language :: Python :: 3.3
Classifier: Programming Language :: Python :: 3.4
Classifier: Programming Language :: Python :: 3.5
Requires-Dist: django
